[
  {
    "title": "analog sky [^o^]",
    "md5": "2d4d0810cd9a1eb07d7b9b996cc45eec",
    "level": "1"
  },
  {
    "title": "Phantom of spring [^o^]",
    "md5": "5c28c61db311a0d3c6e1c0aa9c3f849f",
    "level": "1"
  },
  {
    "title": "Triangular Bullet -L.E.Y- [7Key ^o^]",
    "md5": "803ab8b5b037e7f917cc9c63344a2059",
    "level": "2"
  },
  {
    "title": "cold planet (Oceanfront City Remix) [7keys ^o^]",
    "md5": "6998279997075c93db0956e84880b008",
    "level": "3"
  },
  {
    "title": "なんじゃ村ほいほ～い[AFOTHER+]",
    "md5": "50c7937eb8cf1fa7a1ecfb4a8ac4fd3e",
    "level": "3"
  },
  {
    "title": "osmosis [MANIAC+]",
    "md5": "ab750e5a1f01f5e472f3045141e83cd4",
    "level": "4"
  },
  {
    "title": "G e n g a o z o _ more3y3s",
    "md5": "149c5e51b7b4af7cfa93ba2be6357a71",
    "level": "5"
  },
  {
    "title": "Beatrice [MANIAC]",
    "md5": "64f67cb5e24408f00f85e06c25117a32",
    "level": "8"
  },
  {
    "title": "パッパララッパー[MANIAC]",
    "md5": "fc09d62b2237ec1fdae8020d82ada754",
    "level": "10"
  },
  {
    "title": "パッパララッパー[MANIAC-]",
    "md5": "81a0b10a6c175f2556e2316868f3d8ea",
    "level": "10"
  },
  {
    "title": "Pangaea [tintin--]",
    "md5": "e37309f7259f2a8e9796b33a11257151",
    "level": "11"
  },
  {
    "title": "Shiratsuyu [鹿]",
    "md5": "8879cf9a0a9655b7114d13cec6481a3f",
    "level": "12"
  },
  {
    "title": "Summerland [7key Maniac]",
    "md5": "b054eb55c4473705554a3d8d21896922",
    "level": "12"
  },
  {
    "title": "The Gorilla [MANIAC]",
    "md5": "320d055639a908309e0b911ad9a6c979",
    "level": "13"
  },
  {
    "title": "KYOTO-HOT [ANOTHER]",
    "md5": "5c6f58d789af8f699dfbd94cb3d95713",
    "level": "14"
  },
  {
    "title": "Here we go！(TM edit) [^p^]",
    "md5": "0f0fb017e2a575a8de35f3ffcd8aee10",
    "level": "15"
  },
  {
    "title": "スクラッチマニア！このゆびとまれ！",
    "md5": "f0e849a7d2266bd4d6cd6246f764835d",
    "level": "15"
  },
  {
    "title": "Disaster -Maniac-",
    "md5": "40fc4f5a772b719103827555a202d904",
    "level": "16"
  },
  {
    "title": "Skylanding (MANIAC)",
    "md5": "6be26db196fdeb2012be5933a3efc55d",
    "level": "17"
  },
  {
    "title": "TRILL -DENIM-",
    "md5": "f1991fa28e382f3eaf7be539e844b0ef",
    "level": "17"
  },
  {
    "title": "Disaster -Extra-",
    "md5": "2dececb52fd67950b1e89038b9e27493",
    "level": "18"
  },
  {
    "title": "OSARA magic!! [BLACK ANOTHER]",
    "md5": "33c21d04ac761cc4b73d5989d0877116",
    "level": "18"
  },
  {
    "title": "Merrick",
    "md5": "4a0c12531f7e0e15c2a7f3938842121b",
    "level": "19"
  },
  {
    "title": "Only Diversity [MANIAC]",
    "md5": "fa14380ea45e644b5b7a67f73bf38720",
    "level": "19"
  },
  {
    "title": "PEACE BREAKER [Dystopia]",
    "md5": "620b88673aa7d06a248787d09060d465",
    "level": "19"
  },
  {
    "title": "ラブラブ79.99%急接近！？ ～となりのカレはノコギリ波☆～  [MANIAC]",
    "md5": "f911bf153bc53b38ac05afb7c9b8b3f8",
    "level": "19"
  },
  {
    "title": "Air -KY-",
    "md5": "e4db2bf72023a21403440750cafc93f0",
    "level": "20"
  },
  {
    "title": "marginated [^p^]",
    "md5": "28aded7df8a910b7ca3416274bbcad97",
    "level": "20"
  },
  {
    "title": "ON THE DiSH -enoshima style- [BLACK ANOTHER]",
    "md5": "e0265c49f6218c6196197131d2b4cecf",
    "level": "20"
  },
  {
    "title": "空跳ぶ少女 [EXTREME7]",
    "md5": "81ae4a7752a9c0293d595b0bf0e27309",
    "level": "20"
  },
  {
    "title": "100% VEC2 [Innocence]",
    "md5": "68b46c89b37e73f750ff09a241be03c4",
    "level": "21"
  },
  {
    "title": "Epatoivo LdsRmx [皿うどん]",
    "md5": "c996def7c61ada41159b9b20c831d171",
    "level": "21"
  },
  {
    "title": "絶対的共依存-Codependence-",
    "md5": "3cc376adecd0e196a34a12eb39311146",
    "level": "21"
  },
  {
    "title": "恋愛には奥手だが、そのぶん耳の穴を広げてしまう耳穴系男子 [BEGINNER]",
    "md5": "ae12c478ad5ec374f6ba470ab672c195",
    "level": "21"
  },
  {
    "title": "MY ETHER [MANIAC]",
    "md5": "6dbd8c448e2e5d1dc30c832d5f3de5bd",
    "level": "22"
  },
  {
    "title": "Tethys [EXTREME]",
    "md5": "1d525d971da8b7bd75ca7089024ea256",
    "level": "22"
  },
  {
    "title": "オルゴオル☆ディレイ",
    "md5": "969d51c2d2e34bf07cef084c9ce78bcc",
    "level": "22"
  },
  {
    "title": "Angel dust [7key//^p^]",
    "md5": "4a5edec0fbf97e1f87329d78051a1622",
    "level": "23"
  },
  {
    "title": "Escape From Predicament [MANIAC]",
    "md5": "acaaa5681248b95c62544144d381be92",
    "level": "23"
  },
  {
    "title": "Hybrid Galaxy [MANIAC]",
    "md5": "b58c0e94623bea3008c1cac898dd9cb2",
    "level": "23"
  },
  {
    "title": "お前らどうせ「今回も『JUMP』とか『跳』とか関連の単語をタイトルの中に入れるんだろうなー」とか期待していたんだろう？残念だがそう何度もJUMPネタで行くと思うなよ！俺だってそう何度もJUMP、JUMP言い続けたら飽きられるってことぐらい分かってるんだ！JUMPって言い続けた結果、JUMP本来の単語の意味が薄まるなんて状況にさせてたまるか！！！！(BMS edit)",
    "md5": "ac2ed62daa434c186da67dce788437aa",
    "level": "23"
  },
  {
    "title": "サンバランド -LAST BOSS-",
    "md5": "093a8d66b89944db9e42aa2321b4f637",
    "level": "23"
  },
  {
    "title": "Backside of the world [Maniac]",
    "md5": "bc2fbd42c5ad5f12357c7f912f3e068b",
    "level": "24"
  },
  {
    "title": "Shiratsuyu [ハシュ]",
    "md5": "5b411cd3fc7481bad67d452137c6c259",
    "level": "24"
  },
  {
    "title": "ダークサンバランド -LAST BOSS-",
    "md5": "ebc5946c3de24a01048d1c90cbd5c9d6",
    "level": "24"
  }
]